inejsonstat/__init__.py
inejsonstat/config.yaml
inejsonstat/dimensionEnum.py
inejsonstat/dimension_enum_dc.py
inejsonstat/enumerator_hub.py
inejsonstat/ine_status.py
inejsonstat/inejsonstat.log
inejsonstat/inejsonstat.py
inejsonstat/jsondataset.py
inejsonstat/jsonstatcategory.py
inejsonstat/jsonstatdimension.py
inejsonstat/jsonstatrequest.py
inejsonstat/jsonutil.py
inejsonstat/languages_enum.py
inejsonstat/main_logger.py
inejsonstat/target_enum.py
inejsonstat/url_builder.py
jsonstatpy/__init__.py
jsonstatpy/collection.py
jsonstatpy/dataset.py
jsonstatpy/dimension.py
jsonstatpy/downloader.py
jsonstatpy/exceptions.py
jsonstatpy/parse_functions.py
jsonstatpy/schema.py
jsonstatpy/utility.py
jsonstatpy/value.py
jsonstatpy/version.py
jsonstatpy/cli/__init__.py
jsonstatpy/cli/cli_jsonstat.py
inejsonstat-1.0.18.dist-info/LICENSE.txt
inejsonstat-1.0.18.dist-info/METADATA
inejsonstat-1.0.18.dist-info/WHEEL
inejsonstat-1.0.18.dist-info/top_level.txt
inejsonstat-1.0.18.dist-info/RECORD
