Metadata-Version: 2.1
Name: inejsonstat
Version: 1.0.18
Summary: Library to interact with the INE JSON-Stat API
Home-page: https://github.com/Mlgpigeon/inejsonstat.git
Author: Luis María Salete Cuartero
Author-email: luismasc16@gmail.com
License: MIT License
Platform: UNKNOWN
License-File: LICENSE.txt
Requires-Dist: inejsonstat
Requires-Dist: numpy
Requires-Dist: requests
Requires-Dist: terminaltables
Requires-Dist: click
Requires-Dist: cython
Requires-Dist: pandas
Requires-Dist: aenum
Requires-Dist: pyyaml
Requires-Dist: unidecode
Requires-Dist: datetime
